{
  "nodes": [
    {
      "content": "Azure Authenticator app for mobile phones",
      "pos": [
        28,
        69
      ]
    },
    {
      "content": "Learn how to upgrade to the latest version of Azure Authenticatior.",
      "pos": [
        89,
        156
      ]
    },
    {
      "content": "Moving to the new Azure Authenticator app",
      "pos": [
        512,
        553
      ]
    },
    {
      "content": "With the release of the Azure Authenticator app, available for <bpt id=\"p1\">[</bpt>Windows Phone<ept id=\"p1\">](http://www.windowsphone.com/en-us/store/app/azure-authenticator/03a5b2bf-6066-418f-b569-e8aecbc06e50)</ept>, <bpt id=\"p2\">[</bpt>Android<ept id=\"p2\">](https://play.google.com/store/apps/details?id=com.azure.authenticator)</ept>, and <bpt id=\"p3\">[</bpt>IOS<ept id=\"p3\">](https://itunes.apple.com/us/app/azure-authenticator/id983156458)</ept>, the old Multi-Factor Authentication app is being replaced.",
      "pos": [
        555,
        953
      ]
    },
    {
      "content": "The Multi-Factor Authentication app will continue to work but should you decide to move to the new Azure Authenticator app then this article can assist you.",
      "pos": [
        955,
        1111
      ]
    },
    {
      "content": "How to move to the new Azure Authenticator app",
      "pos": [
        1119,
        1165
      ]
    },
    {
      "pos": [
        1168,
        1208
      ],
      "content": "<bpt id=\"p1\">**</bpt>Step 1:<ept id=\"p1\">**</ept> Install Azure Authenticator."
    },
    {
      "content": "Cloud",
      "pos": [
        1212,
        1217
      ]
    },
    {
      "pos": [
        1286,
        1337
      ],
      "content": "<bpt id=\"p1\">**</bpt>Step 2:<ept id=\"p1\">**</ept> Activate your accounts with the new app"
    },
    {
      "content": "First of all make sure, you have the QR code or code and URL for manual entry handy for the account you’d like to add to the app.",
      "pos": [
        1339,
        1468
      ]
    },
    {
      "content": "<ph id=\"ph1\">[AZURE.NOTE]</ph> Not sure of how to get the QR code?",
      "pos": [
        1472,
        1520
      ]
    },
    {
      "content": "Contact your help desk for assistance.",
      "pos": [
        1521,
        1559
      ]
    },
    {
      "content": "Unable to activate your account with the new app?",
      "pos": [
        1565,
        1614
      ]
    },
    {
      "content": "Contact your help desk.",
      "pos": [
        1615,
        1638
      ]
    },
    {
      "content": "Once you have the QR code in front of you, launch the app.",
      "pos": [
        1643,
        1701
      ]
    },
    {
      "content": "Click +.",
      "pos": [
        1702,
        1710
      ]
    },
    {
      "content": "Cloud",
      "pos": [
        1716,
        1721
      ]
    },
    {
      "content": "This will launch the camera to scan the QR code.",
      "pos": [
        1796,
        1844
      ]
    },
    {
      "content": "If you are unable to scan the QR code, you always have the manual entry option.",
      "pos": [
        1846,
        1925
      ]
    },
    {
      "content": "To confirm that the account is successfully activated, verify that the new account shows up on the accounts pages.",
      "pos": [
        1928,
        2042
      ]
    },
    {
      "content": "Follow this step for all your accounts that you’d like to migrate to the new app.",
      "pos": [
        2046,
        2127
      ]
    },
    {
      "pos": [
        2131,
        2210
      ],
      "content": "<bpt id=\"p1\">**</bpt>Step 3:<ept id=\"p1\">**</ept>  Uninstall the old Multi-Factor Authentication app from your phone."
    },
    {
      "content": "Once you have added all the accounts to the new app uninstall the old app from your phone.",
      "pos": [
        2212,
        2302
      ]
    },
    {
      "content": "Curious how to remove individual accounts from the old app?",
      "pos": [
        2304,
        2363
      ]
    },
    {
      "content": "Tap on the account.",
      "pos": [
        2364,
        2383
      ]
    },
    {
      "content": "You’ll get an option to “Delete”.",
      "pos": [
        2384,
        2417
      ]
    },
    {
      "content": "Cloud",
      "pos": [
        2422,
        2427
      ]
    },
    {
      "content": "Additional Resources",
      "pos": [
        2500,
        2520
      ]
    },
    {
      "content": "Azure Multi-Factor Authentication on MSDN",
      "pos": [
        2527,
        2568
      ]
    },
    {
      "pos": [
        2629,
        2933
      ],
      "content": "Azure Authenticator app for <bpt id=\"p1\">[</bpt>Windows Phone<ept id=\"p1\">](http://www.windowsphone.com/en-us/store/app/azure-authenticator/03a5b2bf-6066-418f-b569-e8aecbc06e50)</ept>, <bpt id=\"p2\">[</bpt>Android<ept id=\"p2\">](https://play.google.com/store/apps/details?id=com.azure.authenticator)</ept>, and <bpt id=\"p3\">[</bpt>IOS<ept id=\"p3\">](https://itunes.apple.com/us/app/azure-authenticator/id983156458)</ept>."
    }
  ],
  "content": "<properties \n    pageTitle=\"Azure Authenticator app for mobile phones\" \n    description=\"Learn how to upgrade to the latest version of Azure Authenticatior.\" \n    services=\"multi-factor-authentication\" \n    documentationCenter=\"\" \n    authors=\"billmath\" \n    manager=\"stevenpo\" \n    editor=\"curtland\"/>\n\n<tags \n    ms.service=\"multi-factor-authentication\" \n    ms.workload=\"identity\" \n    ms.tgt_pltfrm=\"na\" \n    ms.devlang=\"na\" \n    ms.topic=\"article\" \n    ms.date=\"08/24/2015\" \n    ms.author=\"billmath\"/>\n\n\n\n# Moving to the new Azure Authenticator app\n\nWith the release of the Azure Authenticator app, available for [Windows Phone](http://www.windowsphone.com/en-us/store/app/azure-authenticator/03a5b2bf-6066-418f-b569-e8aecbc06e50), [Android](https://play.google.com/store/apps/details?id=com.azure.authenticator), and [IOS](https://itunes.apple.com/us/app/azure-authenticator/id983156458), the old Multi-Factor Authentication app is being replaced.  The Multi-Factor Authentication app will continue to work but should you decide to move to the new Azure Authenticator app then this article can assist you.  \n\n\n## How to move to the new Azure Authenticator app \n\n**Step 1:** Install Azure Authenticator.\n\n![Cloud](./media/multi-factor-authentication-azure-authenticator/home.png)\n\n**Step 2:** Activate your accounts with the new app\n\nFirst of all make sure, you have the QR code or code and URL for manual entry handy for the account you’d like to add to the app.\n\n> [AZURE.NOTE] Not sure of how to get the QR code? Contact your help desk for assistance.\n> \n> Unable to activate your account with the new app? Contact your help desk.\n>\n\n\nOnce you have the QR code in front of you, launch the app. Click +. \n\n\n![Cloud](./media/multi-factor-authentication-azure-authenticator/addaccount.png)\n\nThis will launch the camera to scan the QR code.  If you are unable to scan the QR code, you always have the manual entry option. \n\nTo confirm that the account is successfully activated, verify that the new account shows up on the accounts pages. \n\n\nFollow this step for all your accounts that you’d like to migrate to the new app.\n\n\n\n**Step 3:**  Uninstall the old Multi-Factor Authentication app from your phone.\n\nOnce you have added all the accounts to the new app uninstall the old app from your phone.\n\nCurious how to remove individual accounts from the old app?\nTap on the account. You’ll get an option to “Delete”. \n\n![Cloud](./media/multi-factor-authentication-azure-authenticator/remove.png)\n\n**Additional Resources**\n\n* [Azure Multi-Factor Authentication on MSDN](https://msdn.microsoft.com/library/azure/dn249471.aspx) \n* Azure Authenticator app for [Windows Phone](http://www.windowsphone.com/en-us/store/app/azure-authenticator/03a5b2bf-6066-418f-b569-e8aecbc06e50), [Android](https://play.google.com/store/apps/details?id=com.azure.authenticator), and [IOS](https://itunes.apple.com/us/app/azure-authenticator/id983156458).\n"
}